dokithemejupyter/__init__.py
dokithemejupyter/__main__.py
dokithemejupyter/argument_suggestion.py
dokithemejupyter/arguments.py
dokithemejupyter/constants.py
dokithemejupyter/decorator.py
dokithemejupyter/file_system_tools.py
dokithemejupyter/theme_installer.py
dokithemejupyter/theme_janitor.py
dokithemejupyter/theme_manager.py
dokithemejupyter/themes.py
dokithemejupyter/version.txt
dokithemejupyter/defaults/custom.css
dokithemejupyter/defaults/custom.js
dokithemejupyter/fonts/VictorMono-Italic.ttf
dokithemejupyter/fonts/VictorMono-Regular.ttf
dokithemejupyter/styles/background.less
dokithemejupyter/styles/base.less
dokithemejupyter/styles/sticker.less
dokithemejupyter/styles/themes/01e61500-862c-41cd-b653-48d2ef7b1882.less
dokithemejupyter/styles/themes/0527c6fc-316a-4f80-9459-d92ced0e6492.less
dokithemejupyter/styles/themes/06143cbe-2d51-4423-9a93-73a02c828119.less
dokithemejupyter/styles/themes/12a54623-1f0b-4769-9917-d5267092a605.less
dokithemejupyter/styles/themes/13407818-da66-432b-94e3-fd2192e98118.less
dokithemejupyter/styles/themes/13adffd9-acbe-47af-8101-fa71269a4c5c.less
dokithemejupyter/styles/themes/15e51483-1ccd-46b7-90cf-885cccaaaf2c.less
dokithemejupyter/styles/themes/19b65ec8-133c-4655-a77b-13623d8e97d3.less
dokithemejupyter/styles/themes/1f9697bd-aec1-49ff-bdb4-c37ef8ace62b.less
dokithemejupyter/styles/themes/22d0250f-a33b-409a-9cef-22f5eb69fc3d.less
dokithemejupyter/styles/themes/2d049451-6e89-4325-af38-6ce889991e5b.less
dokithemejupyter/styles/themes/2d1112ac-04ab-4f78-82c4-22e5e2c1754b.less
dokithemejupyter/styles/themes/2eedcc31-b5fa-4b30-b045-6a539e915581.less
dokithemejupyter/styles/themes/2f2dff01-7e0e-4ebc-ab1e-34be2486c66f.less
dokithemejupyter/styles/themes/31d5574d-f56b-408f-81dc-9d44feeb62c2.less
dokithemejupyter/styles/themes/325c5d4d-5614-4c58-b296-18924f2f6928.less
dokithemejupyter/styles/themes/3462121b-b101-406f-8b31-ce04d09b2ef6.less
dokithemejupyter/styles/themes/35422aa4-1396-4e76-8ec6-c5560884df22.less
doki_theme_jupyter-88.1.1.1.0.dist-info/LICENSE
doki_theme_jupyter-88.1.1.1.0.dist-info/METADATA
doki_theme_jupyter-88.1.1.1.0.dist-info/WHEEL
doki_theme_jupyter-88.1.1.1.0.dist-info/entry_points.txt
doki_theme_jupyter-88.1.1.1.0.dist-info/top_level.txt
doki_theme_jupyter-88.1.1.1.0.dist-info/RECORD
