Metadata-Version: 2.1
Name: doki-theme-jupyter
Version: 88.1.1.1.0
Summary: Crunch data with your waifu! Choose a Jupyter Notebook theme based on a girl from various anime series, manga, and visual novels.
Home-page: https://github.com/doki-theme/doki-theme-jupyter
Author: Unthrottled
Author-email: alexsimons9999@gmail.com
Project-URL: Bug Reports, https://github.com/doki-theme/doki-theme-jupyter/issues
Project-URL: Source, https://github.com/doki-theme/doki-theme-jupyter/
Keywords: jupyter,notebook,theme
Classifier: Development Status :: 5 - Production/Stable
Classifier: Intended Audience :: Developers
Classifier: Topic :: Software Development :: Build Tools
Classifier: License :: OSI Approved :: MIT License
Classifier: Programming Language :: Python :: 3.7
Classifier: Programming Language :: Python :: 3.8
Classifier: Programming Language :: Python :: 3.9
Requires-Python: >=3.6, <4
License-File: LICENSE
Requires-Dist: jupyter-core
Requires-Dist: notebook (>=5.6.0)
Requires-Dist: python-Levenshtein (>=0.12.2)
Requires-Dist: lesscpy (~=0.14.0)
Requires-Dist: matplotlib (~=3.3.4)
